{
  "kind": "collectionType",
  "collectionName": "services",
  "info": {
    "singularName": "service",
    "pluralName": "services",
    "displayName": "Leistung",
    "description": ""
  },
  "options": {
    "draftAndPublish": true
  },
  "pluginOptions": {
    "versions": {
      "versioned": true
    }
  },
  "attributes": {
    "name": {
      "type": "string",
      "required": true,
      "unique": true,
      "minLength": 1
    },
    "price": {
      "type": "decimal",
      "required": true,
      "unique": false,
      "min": 0,
      "default": 0
    },
    "type": {
      "type": "relation",
      "relation": "oneToOne",
      "target": "api::type.type"
    }
  }
}
